{
    "baseHP": 60,
    "baseAttack": 60,
    "baseDefense": 50,
    "baseSpAttack": 40,
    "baseSpDefense": 50,
    "baseSpeed": 75,
    "type1": "TYPE_NORMAL",
    "type2": "TYPE_GRASS",
    "catchRate": 190,
    "expYield": 67,
    "evYield_HP": 0,
    "evYield_Attack": 0,
    "evYield_Defense": 0,
    "evYield_SpAttack": 0,
    "evYield_SpDefense": 0,
    "evYield_Speed": 1,
    "item1": "ITEM_NONE",
    "item2": "ITEM_NONE",
    "genderRatio": 50.0,
    "eggCycles": 20,
    "friendship": 50,
    "growthRate": "GROWTH_MEDIUM_FAST",
    "eggGroup1": "EGG_GROUP_FIELD",
    "eggGroup2": "EGG_GROUP_FIELD",
    "ability1": "ABILITY_CHLOROPHYLL",
    "ability2": "ABILITY_SAPSIPPER",
    "safariZoneFleeRate": 0,
    "hiddenAbility": "ABILITY_SERENEGRACE",
    "noFlip": true,
    "egg_moves": [
        "MOVE_FAKETEARS",
        "MOVE_NATURALGIFT",
        "MOVE_SYNTHESIS",
        "MOVE_WORRYSEED",
        "MOVE_ODORSLEUTH",
        "MOVE_AGILITY",
        "MOVE_SLEEPTALK",
        "MOVE_BATONPASS",
        "MOVE_GRASSWHISTLE",
        "MOVE_HEADBUTT",
        "MOVE_TROPKICK"
    ],
    "evolve_to": [
        {
            "method": "EVO_LEVEL",
            "condition": "34",
            "target": "SAWSBUCK_SUMMER",
            "extra": "0"
        }
    ],
    "name": "Deerling",
    "evolve_from": [],
    "location": [
        {
            "route": "Route 14",
            "area": "",
            "method": "Good Rod"
        },
        {
            "route": "Route 14",
            "area": "",
            "method": "Super Rod"
        }
    ],
    "tm": [
        "MOVE_TOXIC",
        "MOVE_HIDDENPOWER",
        "MOVE_SUNNYDAY",
        "MOVE_LIGHTSCREEN",
        "MOVE_PROTECT",
        "MOVE_RAINDANCE",
        "MOVE_GIGADRAIN",
        "MOVE_SAFEGUARD",
        "MOVE_FRUSTRATION",
        "MOVE_SOLARBEAM",
        "MOVE_RETURN",
        "MOVE_SHADOWBALL",
        "MOVE_DOUBLETEAM",
        "MOVE_FACADE",
        "MOVE_SECRETPOWER",
        "MOVE_REST",
        "MOVE_ATTRACT",
        "MOVE_ENERGYBALL",
        "MOVE_ENDURE",
        "MOVE_FLASH",
        "MOVE_THUNDERWAVE",
        "MOVE_SLEEPTALK",
        "MOVE_GRASSKNOT",
        "MOVE_SWAGGER",
        "MOVE_SUBSTITUTE",
        "MOVE_WORKUP",
        "MOVE_WILDCHARGE",
        "MOVE_ROUND",
        "MOVE_ECHOEDVOICE",
        "MOVE_NATURALGIFT",
        "MOVE_NATUREPOWER"
    ],
    "tutor": [
        "MOVE_SNORE",
        "MOVE_WORRYSEED",
        "MOVE_SYNTHESIS",
        "MOVE_BOUNCE",
        "MOVE_SEEDBOMB",
        "MOVE_LASTRESORT",
        "MOVE_CONFIDE",
        "MOVE_BATONPASS",
        "MOVE_FAKETEARS",
        "MOVE_AGILITY",
        "MOVE_GRASSYGLIDE"
    ],
    "learnset": [
        {
            "level": 1,
            "move": "MOVE_TACKLE"
        },
        {
            "level": 1,
            "move": "MOVE_CAMOUFLAGE"
        },
        {
            "level": 4,
            "move": "MOVE_GROWL"
        },
        {
            "level": 7,
            "move": "MOVE_SANDATTACK"
        },
        {
            "level": 10,
            "move": "MOVE_DOUBLEKICK"
        },
        {
            "level": 13,
            "move": "MOVE_LEECHSEED"
        },
        {
            "level": 16,
            "move": "MOVE_FEINTATTACK"
        },
        {
            "level": 20,
            "move": "MOVE_TAKEDOWN"
        },
        {
            "level": 24,
            "move": "MOVE_JUMPKICK"
        },
        {
            "level": 28,
            "move": "MOVE_AROMATHERAPY"
        },
        {
            "level": 32,
            "move": "MOVE_ENERGYBALL"
        },
        {
            "level": 36,
            "move": "MOVE_CHARM"
        },
        {
            "level": 41,
            "move": "MOVE_NATUREPOWER"
        },
        {
            "level": 46,
            "move": "MOVE_DOUBLEEDGE"
        },
        {
            "level": 51,
            "move": "MOVE_SOLARBEAM"
        }
    ]
}