{
    "baseHP": 130,
    "baseAttack": 65,
    "baseDefense": 60,
    "baseSpAttack": 110,
    "baseSpDefense": 95,
    "baseSpeed": 65,
    "type1": "TYPE_WATER",
    "type2": "TYPE_WATER",
    "catchRate": 45,
    "expYield": 196,
    "evYield_HP": 2,
    "evYield_Attack": 0,
    "evYield_Defense": 0,
    "evYield_SpAttack": 0,
    "evYield_SpDefense": 0,
    "evYield_Speed": 0,
    "item1": "ITEM_NONE",
    "item2": "ITEM_NONE",
    "genderRatio": 12.5,
    "eggCycles": 35,
    "friendship": 50,
    "growthRate": "GROWTH_MEDIUM_FAST",
    "eggGroup1": "EGG_GROUP_FIELD",
    "eggGroup2": "EGG_GROUP_FIELD",
    "ability1": "ABILITY_WATERABSORB",
    "ability2": "ABILITY_WATERABSORB",
    "safariZoneFleeRate": 0,
    "hiddenAbility": "ABILITY_HYDRATION",
    "noFlip": true,
    "name": "Vaporeon",
    "evolve_from": [],
    "location": [
        {
            "route": "Route 14",
            "area": "",
            "method": "Good Rod"
        },
        {
            "route": "Route 14",
            "area": "",
            "method": "Super Rod"
        }
    ],
    "learnset": [
        {
            "level": 0,
            "move": "MOVE_WATERGUN"
        },
        {
            "level": 1,
            "move": "MOVE_COVET"
        },
        {
            "level": 1,
            "move": "MOVE_SWIFT"
        },
        {
            "level": 1,
            "move": "MOVE_BITE"
        },
        {
            "level": 1,
            "move": "MOVE_COPYCAT"
        },
        {
            "level": 1,
            "move": "MOVE_BATONPASS"
        },
        {
            "level": 1,
            "move": "MOVE_TAKEDOWN"
        },
        {
            "level": 1,
            "move": "MOVE_CHARM"
        },
        {
            "level": 1,
            "move": "MOVE_DOUBLEEDGE"
        },
        {
            "level": 1,
            "move": "MOVE_TRUMPCARD"
        },
        {
            "level": 1,
            "move": "MOVE_HELPINGHAND"
        },
        {
            "level": 1,
            "move": "MOVE_TACKLE"
        },
        {
            "level": 1,
            "move": "MOVE_GROWL"
        },
        {
            "level": 1,
            "move": "MOVE_TAILWHIP"
        },
        {
            "level": 1,
            "move": "MOVE_WATERGUN"
        },
        {
            "level": 5,
            "move": "MOVE_SANDATTACK"
        },
        {
            "level": 10,
            "move": "MOVE_QUICKATTACK"
        },
        {
            "level": 15,
            "move": "MOVE_BABYDOLLEYES"
        },
        {
            "level": 20,
            "move": "MOVE_HAZE"
        },
        {
            "level": 25,
            "move": "MOVE_WATERPULSE"
        },
        {
            "level": 30,
            "move": "MOVE_AURORABEAM"
        },
        {
            "level": 35,
            "move": "MOVE_AQUARING"
        },
        {
            "level": 40,
            "move": "MOVE_MUDDYWATER"
        },
        {
            "level": 45,
            "move": "MOVE_ACIDARMOR"
        },
        {
            "level": 50,
            "move": "MOVE_HYDROPUMP"
        },
        {
            "level": 55,
            "move": "MOVE_LASTRESORT"
        }
    ],
    "tm": [
        "MOVE_WATERPULSE",
        "MOVE_CALMMIND",
        "MOVE_ROAR",
        "MOVE_TOXIC",
        "MOVE_HAIL",
        "MOVE_HIDDENPOWER",
        "MOVE_SUNNYDAY",
        "MOVE_ICEBEAM",
        "MOVE_BLIZZARD",
        "MOVE_HYPERBEAM",
        "MOVE_PROTECT",
        "MOVE_RAINDANCE",
        "MOVE_FRUSTRATION",
        "MOVE_IRONTAIL",
        "MOVE_RETURN",
        "MOVE_DIG",
        "MOVE_SHADOWBALL",
        "MOVE_DOUBLETEAM",
        "MOVE_FACADE",
        "MOVE_SECRETPOWER",
        "MOVE_REST",
        "MOVE_ATTRACT",
        "MOVE_BRINE",
        "MOVE_ENDURE",
        "MOVE_GIGAIMPACT",
        "MOVE_SLEEPTALK",
        "MOVE_SCALD",
        "MOVE_SWAGGER",
        "MOVE_SUBSTITUTE",
        "MOVE_WORKUP",
        "MOVE_ROUND",
        "MOVE_ECHOEDVOICE",
        "MOVE_NATURALGIFT",
        "MOVE_SURF",
        "MOVE_STRENGTH",
        "MOVE_DIVE",
        "MOVE_ROCKSMASH",
        "MOVE_WATERFALL"
    ],
    "tutor": [
        "MOVE_SNORE",
        "MOVE_HEALBELL",
        "MOVE_HELPINGHAND",
        "MOVE_COVET",
        "MOVE_SIGNALBEAM",
        "MOVE_AQUATAIL",
        "MOVE_ICYWIND",
        "MOVE_LASERFOCUS",
        "MOVE_LIQUIDATION",
        "MOVE_HYPERVOICE",
        "MOVE_LASTRESORT",
        "MOVE_CONFIDE",
        "MOVE_FOCUSENERGY",
        "MOVE_BATONPASS",
        "MOVE_FAKETEARS",
        "MOVE_WHIRLPOOL",
        "MOVE_BODYSLAM",
        "MOVE_STOREDPOWER",
        "MOVE_WEATHERBALL",
        "MOVE_MUDDYWATER",
        "MOVE_HYDROPUMP",
        "MOVE_FLIPTURN"
    ]
}